debayer_ohweier/__init__.py
debayer_ohweier/functions.py
debayer_ohweier-0.0.1.dist-info/METADATA
debayer_ohweier-0.0.1.dist-info/WHEEL
debayer_ohweier-0.0.1.dist-info/top_level.txt
debayer_ohweier-0.0.1.dist-info/RECORD
