Metadata-Version: 2.1
Name: debayer-ohweier
Version: 0.0.1
Summary: Small toolkit to debayer and stack images.
Home-page: UNKNOWN
Author: Jan Paschen
Author-email: jan@ej-paschen.de
License: UNKNOWN
Keywords: python
Platform: UNKNOWN
Classifier: Programming Language :: Python :: 3
Classifier: License :: OSI Approved :: MIT License
Classifier: Operating System :: OS Independent
Requires-Python: >=3.6
Requires-Dist: matplotlib
Requires-Dist: numpy
Requires-Dist: opencv-python
